sympla/__init__.py
sympla/enums.py
sympla/sympla.py
sympla-0.1.4.dist-info/LICENSE
sympla-0.1.4.dist-info/METADATA
sympla-0.1.4.dist-info/WHEEL
sympla-0.1.4.dist-info/RECORD
