Metadata-Version: 2.1
Name: sympla
Version: 0.1.4
Summary: A plataforma online de eventos líder no Brasil. Venda de ingressos, promoção e administração de eventos. Simples e segura. Organiza eventos? Sympla!
Home-page: https://github.com/hudsonbrendon/sympla#readme
License: MIT
Author: Hudson Brendon
Author-email: contato.hudsonbrendon@gmail.com
Requires-Python: >=3.8,<4.0
Classifier: License :: OSI Approved :: MIT License
Classifier: Programming Language :: Python :: 3
Classifier: Programming Language :: Python :: 3.8
Classifier: Programming Language :: Python :: 3.9
Classifier: Programming Language :: Python :: 3.10
Classifier: Programming Language :: Python :: 3.11
Classifier: Programming Language :: Python :: 3.12
Classifier: Programming Language :: Python :: 3.13
Requires-Dist: pytest-sugar (>=1.0.0,<2.0.0)
Requires-Dist: requests (>=2.28.1,<3.0.0)
Requires-Dist: requests-mock (>=1.12.1,<2.0.0)
Project-URL: Repository, https://github.com/hudsonbrendon/sympla
